[
    {
        "index": 0,
        "title": "TITLE-0",
        "description": "INFORMATION-0",
        "image": "IMAGE",
        "linkRepo": "GITHUB",
        "linkLive": "URL"
    },
    {
        "index": 1,
        "title": "TITLE-1",
        "description": "INFORMATION-1",
        "image": "IMAGE",
        "linkRepo": "GITHUB",
        "linkLive": "URL"
    },
    {
        "index": 2,
        "title": "TITLE-2",
        "description": "INFORMATION-2",
        "image": "IMAGE",
        "linkRepo": "GITHUB",
        "linkLive": "URL"
    }
]